[
    {
        "uid": "c99be640",
        "axes": [
            [
                0.38218739333578405,
                0.9173838039819415,
                0.11108443890492553
            ],
            [
                0.895623261166247,
                -0.3973346785911715,
                0.19996031417955806
            ],
            [
                0.22757805349623622,
                0.023067496189962386,
                -0.9734865793560744
            ]
        ],
        "hyperbolic_axes": [
            31478.426926200893,
            9.329770098115734,
            0.8175618927101572
        ],
        "max_angular_error": 16.489943565932563,
        "min_angular_error": 0.2919931627401503,
        "strike": 174.212220519033,
        "dip": 13.223145069338642,
        "rake": 60.946408481675725,
        "disabled": false,
        "name": "poorly_defined"
    },
    {
        "uid": "3a2324ee",
        "axes": [
            [
                0.9957849370018035,
                -0.06900412028116694,
                -0.06042177276889991
            ],
            [
                -0.06959504589200638,
                -0.9975453890807541,
                -0.007728279952054162
            ],
            [
                -0.059740177666323065,
                0.011900760813916222,
                -0.998143017339923
            ]
        ],
        "hyperbolic_axes": [
            21621.15722931624,
            2075.3675468612746,
            0.1428065892232801
        ],
        "max_angular_error": 0.4752687770349794,
        "min_angular_error": 0.14725034875800813,
        "strike": 11.266329335065905,
        "dip": 3.492277804823118,
        "rake": 172.71112822445517,
        "disabled": false,
        "name": "well_defined"
    }
]